iliantest/__init__.py
iliantest-0.0.1.dist-info/METADATA
iliantest-0.0.1.dist-info/WHEEL
iliantest-0.0.1.dist-info/top_level.txt
iliantest-0.0.1.dist-info/RECORD
